Workbook

Sheet Expense Tracker
A1: Simple Expense Tracker
A2: Veda Technology – Data Analytics Track
A4: Date | B4: Description | C4: Category | D4: Payment Method | E4: Amount (₹) | F4: Month
A5: 46024 | B5: House Rent | C5: Housing | D5: Bank Transfer | E5: 9000 | F5: =TEXT(A5,"mmm-yyyy")
A6: 46026 | B6: Groceries | C6: Food | D6: UPI | E6: 1850 | F6: =TEXT(A6,"mmm-yyyy")
A7: 46029 | B7: Metro/Bus | C7: Transport | D7: UPI | E7: 620 | F7: =TEXT(A7,"mmm-yyyy")
A8: 46032 | B8: Mobile Recharge | C8: Bills | D8: UPI | E8: 399 | F8: =TEXT(A8,"mmm-yyyy")
A9: 46035 | B9: Internet Bill | C9: Bills | D9: UPI | E9: 599 | F9: =TEXT(A9,"mmm-yyyy")
A10: 46038 | B10: Lunch | C10: Food | D10: Cash | E10: 280 | F10: =TEXT(A10,"mmm-yyyy")
A11: 46042 | B11: Movie | C11: Entertainment | D11: UPI | E11: 450 | F11: =TEXT(A11,"mmm-yyyy")
A12: 46046 | B12: Medicines | C12: Health | D12: UPI | E12: 520 | F12: =TEXT(A12,"mmm-yyyy")
A13: 46049 | B13: Clothes | C13: Shopping | D13: Card | E13: 1200 | F13: =TEXT(A13,"mmm-yyyy")
A14: 46052 | B14: Electricity Bill | C14: Bills | D14: UPI | E14: 760 | F14: =TEXT(A14,"mmm-yyyy")
A15: 46055 | B15: House Rent | C15: Housing | D15: Bank Transfer | E15: 9000 | F15: =TEXT(A15,"mmm-yyyy")
A16: 46058 | B16: Groceries | C16: Food | D16: UPI | E16: 2100 | F16: =TEXT(A16,"mmm-yyyy")
... A33: 46111 | B33: Electricity Bill | C33: Bills | D33: UPI | E33: 780 | F33: =TEXT(A33,"mmm-yyyy")
D35: Total Expenses | E35: =SUM(E5:E33)

Sheet Monthly Summary
A1: Monthly Expense Summary
A2: Expense totals by month and category
A4: Category | B4: Jan-2026 | C4: Feb-2026 | D4: Mar-2026 | E4: 3-Month Total | G4: Category | H4: 3-Month Total
A5: Food | B5: =SUMIFS('Expense Tracker'!$E$5:$E$33,'Expense Tracker'!$C$5:$C$33,$A5,'Expense Tracker'!$F$5:$F$33,B$4) | C5: =SUMIFS('Expense Tracker'!$E$5:$E$33,'Expense Tracker'!$C$5:$C$33,$A5,'Expense Tracker'!$F$5:$F$33,C$4) | D5: =SUMIFS('Expense Tracker'!$E$5:$E$33,'Expense Tracker'!$C$5:$C$33,$A5,'Expense Tracker'!$F$5:$F$33,D$4) | E5: =SUM(B5:D5) | G5: Food | H5: =E5
A6: Transport | B6: =SUMIFS('Expense Tracker'!$E$5:$E$33,'Expense Tracker'!$C$5:$C$33,$A6,'Expense Tracker'!$F$5:$F$33,B$4) | C6: =SUMIFS('Expense Tracker'!$E$5:$E$33,'Expense Tracker'!$C$5:$C$33,$A6,'Expense Tracker'!$F$5:$F$33,C$4) | D6: =SUMIFS('Expense Tracker'!$E$5:$E$33,'Expense Tracker'!$C$5:$C$33,$A6,'Expense Tracker'!$F$5:$F$33,D$4) | E6: =SUM(B6:D6) | G6: Transport | H6: =E6
A7: Housing | B7: =SUMIFS('Expense Tracker'!$E$5:$E$33,'Expense Tracker'!$C$5:$C$33,$A7,'Expense Tracker'!$F$5:$F$33,B$4) | C7: =SUMIFS('Expense Tracker'!$E$5:$E$33,'Expense Tracker'!$C$5:$C$33,$A7,'Expense Tracker'!$F$5:$F$33,C$4) | D7: =SUMIFS('Expense Tracker'!$E$5:$E$33,'Expense Tracker'!$C$5:$C$33,$A7,'Expense Tracker'!$F$5:$F$33,D$4) | E7: =SUM(B7:D7) | G7: Housing | H7: =E7
A8: Bills | B8: =SUMIFS('Expense Tracker'!$E$5:$E$33,'Expense Tracker'!$C$5:$C$33,$A8,'Expense Tracker'!$F$5:$F$33,B$4) | C8: =SUMIFS('Expense Tracker'!$E$5:$E$33,'Expense Tracker'!$C$5:$C$33,$A8,'Expense Tracker'!$F$5:$F$33,C$4) | D8: =SUMIFS('Expense Tracker'!$E$5:$E$33,'Expense Tracker'!$C$5:$C$33,$A8,'Expense Tracker'!$F$5:$F$33,D$4) | E8: =SUM(B8:D8) | G8: Bills | H8: =E8
A9: Entertainment | B9: =SUMIFS('Expense Tracker'!$E$5:$E$33,'Expense Tracker'!$C$5:$C$33,$A9,'Expense Tracker'!$F$5:$F$33,B$4) | C9: =SUMIFS('Expense Tracker'!$E$5:$E$33,'Expense Tracker'!$C$5:$C$33,$A9,'Expense Tracker'!$F$5:$F$33,C$4) | D9: =SUMIFS('Expense Tracker'!$E$5:$E$33,'Expense Tracker'!$C$5:$C$33,$A9,'Expense Tracker'!$F$5:$F$33,D$4) | E9: =SUM(B9:D9) | G9: Entertainment | H9: =E9
A10: Health | B10: =SUMIFS('Expense Tracker'!$E$5:$E$33,'Expense Tracker'!$C$5:$C$33,$A10,'Expense Tracker'!$F$5:$F$33,B$4) | C10: =SUMIFS('Expense Tracker'!$E$5:$E$33,'Expense Tracker'!$C$5:$C$33,$A10,'Expense Tracker'!$F$5:$F$33,C$4) | D10: =SUMIFS('Expense Tracker'!$E$5:$E$33,'Expense Tracker'!$C$5:$C$33,$A10,'Expense Tracker'!$F$5:$F$33,D$4) | E10: =SUM(B10:D10) | G10: Health | H10: =E10
A11: Shopping | B11: =SUMIFS('Expense Tracker'!$E$5:$E$33,'Expense Tracker'!$C$5:$C$33,$A11,'Expense Tracker'!$F$5:$F$33,B$4) | C11: =SUMIFS('Expense Tracker'!$E$5:$E$33,'Expense Tracker'!$C$5:$C$33,$A11,'Expense Tracker'!$F$5:$F$33,C$4) | D11: =SUMIFS('Expense Tracker'!$E$5:$E$33,'Expense Tracker'!$C$5:$C$33,$A11,'Expense Tracker'!$F$5:$F$33,D$4) | E11: =SUM(B11:D11) | G11: Shopping | H11: =E11
A12: Education | B12: =SUMIFS('Expense Tracker'!$E$5:$E$33,'Expense Tracker'!$C$5:$C$33,$A12,'Expense Tracker'!$F$5:$F$33,B$4) | C12: =SUMIFS('Expense Tracker'!$E$5:$E$33,'Expense Tracker'!$C$5:$C$33,$A12,'Expense Tracker'!$F$5:$F$33,C$4) | D12: =SUMIFS('Expense Tracker'!$E$5:$E$33,'Expense Tracker'!$C$5:$C$33,$A12,'Expense Tracker'!$F$5:$F$33,D$4) | E12: =SUM(B12:D12) | G12: Education | H12: =E12
A13: Other | B13: =SUMIFS('Expense Tracker'!$E$5:$E$33,'Expense Tracker'!$C$5:$C$33,$A13,'Expense Tracker'!$F$5:$F$33,B$4) | C13: =SUMIFS('Expense Tracker'!$E$5:$E$33,'Expense Tracker'!$C$5:$C$33,$A13,'Expense Tracker'!$F$5:$F$33,C$4) | D13: =SUMIFS('Expense Tracker'!$E$5:$E$33,'Expense Tracker'!$C$5:$C$33,$A13,'Expense Tracker'!$F$5:$F$33,D$4) | E13: =SUM(B13:D13) | G13: Other | H13: =E13
A14: Total | B14: =SUM(B5:B13) | C14: =SUM(C5:C13) | D14: =SUM(D5:D13) | E14: =SUM(E5:E13)

Sheet README
A1: Project Notes – Simple Expense Tracker
A3: Objective | B3: Build a monthly personal/business expense summary and practice categorization and totals.
A4: Tools | B4: Microsoft Excel
A5: Deliverables | B5: Expense tracker + monthly summary + category analysis
A7: How to use | B7: Enter Date, Description, Category, Payment Method and Amount in the Expense Tracker. The Month column and Monthly Summary update through formulas.
A9: Interview Question 1 | B9: Fixed vs variable expense?
A10: Answer | B10: Fixed expenses usually stay similar each month, such as rent. Variable expenses change based on usage or needs, such as groceries, fuel and entertainment.
A12: Interview Question 2 | B12: Why categorize expenses?
A13: Answer | B13: Categorizing expenses makes it easier to see where money is going, compare spending across months and identify areas where spending can be controlled.
A15: Validation | B15: Totals are formula-based and the category/payment fields include dropdown validation.
